tofea/__init__.py
tofea/elements.py
tofea/fea2d.py
tofea/primitives.py
tofea/solvers.py
tofea-0.1.0.dist-info/LICENSE
tofea-0.1.0.dist-info/WHEEL
tofea-0.1.0.dist-info/METADATA
tofea-0.1.0.dist-info/RECORD
