Metadata-Version: 2.1
Name: tofea
Version: 0.1.0
Summary: Simple Finite Element Analysis for Topology Optimization
Author: Yannick Augenstein
Requires-Python: >=3.10,<=3.12
Classifier: Programming Language :: Python :: 3.10
Classifier: Programming Language :: Python :: 3.11
Requires-Dist: numpy
Requires-Dist: scipy
Requires-Dist: sympy
Requires-Dist: autograd
Requires-Dist: tofea[tests,examples] ; extra == "all"
Requires-Dist: tofea[all] ; extra == "dev"
Requires-Dist: ruff ; extra == "dev"
Requires-Dist: mypy ; extra == "dev"
Requires-Dist: pre-commit ; extra == "dev"
Requires-Dist: nlopt ; extra == "examples"
Requires-Dist: matplotlib ; extra == "examples"
Requires-Dist: pytest ; extra == "tests"
Requires-Dist: pytest-cov ; extra == "tests"
Project-URL: Source, https://github.com/mrbaozi/tofea
Provides-Extra: all
Provides-Extra: dev
Provides-Extra: examples
Provides-Extra: tests
